COPYING
MANIFEST.in
README.md
setup.cfg
setup.py
cobe/__init__.py
cobe/bot.py
cobe/brain.py
cobe/commands.py
cobe/control.py
cobe/instatrace.py
cobe/scoring.py
cobe/tokenizers.py
cobe.egg-info/PKG-INFO
cobe.egg-info/SOURCES.txt
cobe.egg-info/dependency_links.txt
cobe.egg-info/entry_points.txt
cobe.egg-info/requires.txt
cobe.egg-info/top_level.txt